{
    "C1": {
        "train": [
            21,
            38,
            18,
            14,
            28
        ],
        "test": [
            11,
            19
        ]
    },
    "C2": {
        "train": [
            29,
            12,
            6,
            22,
            42
        ],
        "test": [
            25,
            27
        ]
    },
    "C3": {
        "train": [
            39,
            2,
            35,
            8,
            36,
            34,
            23
        ],
        "test": [
            13,
            33,
            30
        ]
    },
    "C4": {
        "train": [
            15,
            16,
            3,
            17,
            10,
            4
        ],
        "test": [
            37,
            1,
            41
        ]
    },
    "C5": {
        "train": [
            40,
            26,
            31,
            0,
            7,
            9,
            5
        ],
        "test": [
            20,
            24,
            32
        ]
    }
}