{
    "C1": {
        "train": [
            437,
            707,
            630,
            140,
            337,
            695,
            463,
            955,
            246,
            468,
            381,
            668,
            643,
            461,
            155,
            873,
            361,
            717,
            309,
            971,
            902,
            130,
            433,
            273,
            349,
            624,
            60,
            579,
            102,
            88,
            894,
            771,
            385,
            379,
            581,
            954,
            635,
            949,
            933,
            892,
            958,
            241,
            284,
            471,
            640,
            637,
            953,
            33,
            1027,
            1042,
            268,
            434,
            738,
            151,
            15,
            496,
            446,
            1040,
            253,
            206,
            992,
            767,
            181,
            283,
            202,
            220,
            693,
            791,
            127,
            237,
            715,
            295,
            187,
            551,
            605,
            740,
            898,
            706,
            3,
            533,
            590,
            372,
            616,
            909,
            818,
            72,
            190,
            638,
            603,
            230,
            676,
            781,
            912,
            255,
            314,
            823,
            943,
            956,
            975,
            729,
            322,
            828,
            116,
            597,
            489,
            115,
            705,
            0,
            76,
            702,
            995,
            363,
            666,
            692,
            608,
            233,
            287,
            620,
            124,
            488,
            161,
            766,
            795,
            415,
            745,
            893,
            279,
            35,
            271,
            824,
            553,
            757,
            989,
            588,
            196,
            527,
            564,
            1029,
            977,
            647,
            338,
            205,
            388,
            519,
            667,
            790,
            900,
            978,
            106,
            1005,
            257,
            466,
            300,
            534,
            765,
            1013,
            827,
            83,
            944,
            854,
            780,
            342,
            983,
            794,
            583,
            1003,
            427,
            97,
            113,
            536,
            567,
            185,
            168,
            330,
            731,
            650,
            91,
            459
        ],
        "test": [
            997,
            710,
            18,
            739,
            936,
            549,
            510,
            915,
            837,
            134,
            457,
            275,
            542,
            158,
            883,
            998,
            896,
            263,
            884,
            84,
            788,
            494,
            921,
            391,
            245,
            153,
            419,
            85,
            413,
            1037,
            27,
            797,
            423,
            430,
            2,
            988,
            331,
            919,
            289,
            1036,
            684,
            916,
            600,
            1034,
            374,
            156,
            445,
            503,
            347,
            320,
            11,
            225,
            646,
            165,
            585,
            629,
            316,
            399,
            1039,
            145
        ]
    },
    "C2": {
        "train": [
            950,
            803,
            394,
            910,
            5,
            743,
            879,
            822,
            874,
            477,
            751,
            443,
            963,
            195,
            315,
            895,
            925,
            305,
            491,
            353,
            389,
            622,
            959,
            92,
            850,
            876,
            432,
            274,
            428,
            604,
            951,
            319,
            6,
            741,
            808,
            595,
            212,
            1023,
            550,
            593,
            416,
            71,
            224,
            518,
            945,
            863,
            455,
            47,
            753,
            209,
            247,
            940,
            672,
            375,
            920,
            307,
            369,
            98,
            613,
            928,
            481,
            371,
            907,
            725,
            51,
            460,
            607,
            294,
            870,
            46,
            1035,
            929,
            516,
            506,
            1016,
            685,
            377,
            56,
            816,
            560,
            166,
            298,
            937,
            584,
            721,
            277,
            112,
            109,
            504,
            576,
            644,
            566,
            358,
            270,
            144,
            970,
            444,
            234,
            559,
            752,
            333,
            623,
            442,
            773,
            642,
            691,
            376,
            602,
            591,
            324,
            994,
            557,
            346,
            1025,
            213,
            748,
            587,
            227,
            467,
            398,
            966,
            758,
            291,
            254,
            296,
            341,
            1020,
            525,
            306,
            750,
            334,
            772,
            135,
            897,
            521,
            885,
            194,
            68,
            393,
            730,
            817,
            1021,
            844,
            888,
            362,
            872,
            357,
            73,
            65,
            182,
            801,
            458,
            179,
            522,
            218,
            865,
            473,
            340,
            378,
            86,
            973,
            789
        ],
        "test": [
            927,
            1033,
            840,
            799,
            1014,
            486,
            219,
            941,
            523,
            191,
            265,
            886,
            659,
            805,
            704,
            426,
            136,
            501,
            350,
            49,
            48,
            926,
            414,
            117,
            30,
            335,
            855,
            82,
            20,
            1038,
            147,
            531,
            465,
            793,
            582,
            509,
            911,
            539,
            698,
            10,
            990,
            866,
            881,
            201,
            657,
            632,
            658,
            853,
            1017,
            317,
            1001,
            366,
            470,
            511
        ]
    },
    "C3": {
        "train": [
            901,
            252,
            719,
            339,
            964,
            497,
            820,
            397,
            58,
            555,
            930,
            867,
            786,
            826,
            838,
            609,
            217,
            852,
            276,
            1006,
            429,
            89,
            487,
            167,
            572,
            1015,
            979,
            660,
            164,
            111,
            942,
            875,
            249,
            203,
            905,
            505,
            687,
            150,
            708,
            948,
            222,
            724,
            55,
            450,
            810,
            675,
            1030,
            986,
            264,
            628,
            981,
            924,
            778,
            438,
            735,
            967,
            625,
            649,
            984,
            716,
            746,
            889,
            238,
            216,
            996,
            157,
            400,
            395,
            934,
            636,
            712,
            524,
            517,
            21,
            244,
            732,
            515,
            36,
            783,
            589,
            472,
            677,
            424,
            947,
            152,
            326,
            580,
            208,
            882,
            493,
            110,
            242,
            578,
            485,
            957,
            991,
            513,
            308,
            922,
            336,
            546,
            614,
            733,
            543,
            763,
            843,
            26,
            125,
            571,
            250,
            982,
            697,
            297,
            421,
            800,
            639,
            37,
            94,
            146,
            777,
            764,
            779,
            479,
            431,
            293,
            74,
            577,
            804,
            43,
            321,
            556,
            526,
            931,
            563,
            862,
            81,
            364,
            411
        ],
        "test": [
            775,
            368,
            834,
            310,
            552,
            861,
            12,
            669,
            78,
            495,
            661,
            1010,
            914,
            718,
            848,
            633,
            103,
            774,
            456,
            723,
            1011,
            119,
            864,
            621,
            836,
            829,
            207,
            596,
            311,
            23,
            67,
            176,
            40,
            686,
            77,
            611,
            830,
            645,
            64,
            422,
            651,
            17,
            761,
            290,
            59,
            52,
            727
        ]
    },
    "C4": {
        "train": [
            239,
            154,
            1008,
            1048,
            1028,
            280,
            671,
            678,
            267,
            75,
            703,
            756,
            318,
            8,
            39,
            386,
            90,
            547,
            66,
            663,
            680,
            365,
            439,
            617,
            121,
            390,
            171,
            215,
            475,
            304,
            932,
            938,
            243,
            627,
            454,
            380,
            221,
            610,
            665,
            868,
            4,
            404,
            142,
            908,
            406,
            512,
            332,
            694,
            87,
            408,
            880,
            231,
            210,
            118,
            352,
            683,
            869,
            784,
            906,
            462,
            664,
            288,
            890,
            891,
            845,
            841,
            535,
            286,
            262,
            345,
            965,
            170,
            137,
            114,
            529,
            654,
            232,
            812,
            240,
            359,
            1000,
            131,
            160,
            480,
            31,
            266,
            16,
            969,
            123,
            993,
            498,
            1007,
            260,
            228,
            961,
            490,
            688,
            1012,
            1002,
            45,
            251,
            188,
            373,
            857,
            976,
            747,
            22,
            760,
            80,
            418,
            282,
            878,
            754,
            670,
            835,
            690,
            199,
            313,
            259,
            814,
            24,
            34,
            451
        ],
        "test": [
            641,
            548,
            53,
            652,
            540,
            204,
            599,
            1045,
            1041,
            601,
            392,
            532,
            483,
            502,
            453,
            1009,
            62,
            1,
            514,
            507,
            162,
            189,
            1019,
            436,
            1044,
            634,
            285,
            565,
            700,
            96,
            737,
            269,
            173,
            923,
            149,
            169,
            858,
            464,
            499,
            918,
            403
        ]
    },
    "C5": {
        "train": [
            570,
            825,
            229,
            197,
            615,
            41,
            174,
            815,
            594,
            172,
            129,
            95,
            899,
            351,
            474,
            214,
            575,
            871,
            108,
            1018,
            383,
            235,
            856,
            348,
            618,
            807,
            356,
            762,
            128,
            736,
            32,
            720,
            785,
            248,
            148,
            278,
            749,
            344,
            9,
            292,
            626,
            402,
            903,
            192,
            769,
            132,
            159,
            100,
            544,
            537,
            561,
            849,
            301,
            178,
            839,
            126,
            541,
            299,
            435,
            859,
            985,
            57,
            831,
            592,
            107,
            904,
            412,
            689,
            759,
            105,
            410,
            711,
            545,
            887,
            61,
            396,
            449,
            14,
            574,
            272,
            223,
            768,
            832,
            946,
            847,
            138,
            441,
            520,
            478,
            407,
            1031,
            425,
            987,
            726,
            787,
            674,
            734,
            699,
            722,
            469,
            42,
            29,
            538,
            962,
            798,
            833,
            226,
            530,
            13,
            673,
            484,
            177,
            256,
            54,
            573,
            261,
            713,
            382,
            63,
            701,
            387,
            809,
            742,
            1024,
            482,
            258,
            860,
            44,
            355,
            619,
            38,
            492,
            28,
            792,
            917,
            99,
            653,
            183,
            476,
            329,
            367,
            200,
            806,
            682,
            554,
            586,
            796,
            782,
            980,
            281,
            508,
            558,
            728,
            211,
            811,
            913,
            163,
            141,
            370,
            325,
            70,
            447,
            122,
            401,
            343,
            101,
            656,
            409,
            354,
            420,
            69,
            405,
            612,
            968,
            842,
            606,
            1004,
            1026,
            819,
            681,
            328,
            568,
            662,
            133
        ],
        "test": [
            1032,
            770,
            7,
            939,
            184,
            952,
            417,
            236,
            175,
            384,
            679,
            1043,
            360,
            776,
            25,
            1046,
            846,
            452,
            120,
            440,
            327,
            935,
            972,
            1022,
            448,
            500,
            198,
            312,
            180,
            569,
            974,
            821,
            303,
            562,
            877,
            631,
            714,
            648,
            139,
            19,
            851,
            323,
            528,
            709,
            143,
            813,
            744,
            960,
            598,
            999,
            79,
            755,
            802,
            1047,
            186,
            655,
            104,
            193,
            302,
            50,
            93,
            696
        ]
    }
}